calfem/__init__.py
calfem/_export.py
calfem/classes_qt4.py
calfem/classes_wx.py
calfem/core.py
calfem/core_compat.py
calfem/editor.py
calfem/editor.ui
calfem/editor_resources.py
calfem/editor_scene.py
calfem/editor_ui.py
calfem/experimental.py
calfem/geometry.py
calfem/intvis.py
calfem/matrix_compat.py
calfem/mesh.py
calfem/misc.py
calfem/qt5.py
calfem/shapes.py
calfem/solver.py
calfem/ui.py
calfem/utils.py
calfem/vedo_utils.py
calfem/vis.py
calfem/vis_mpl.py
calfem/vis_vedo.py
calfem/vis_vedo_utils.py
calfem/vis_vtk.py
calfem_python-3.6.13.dist-info/METADATA
calfem_python-3.6.13.dist-info/WHEEL
calfem_python-3.6.13.dist-info/entry_points.txt
calfem_python-3.6.13.dist-info/licenses/LICENSE
calfem_python-3.6.13.dist-info/licenses/LICENSE.txt
calfem_python-3.6.13.dist-info/RECORD
