Metadata-Version: 2.1
Name: calfem-python
Version: 3.6.13
Summary: CALFEM for Python
Keywords: finite element,math,numerics
Author-Email: Jonas Lindemann <jonas.lindemann@lunarc.lu.se>, Jonas Lindemann <jonas.lindemann@gmail.com>
License: MIT
Classifier: Development Status :: 4 - Beta
Classifier: Intended Audience :: Developers
Classifier: License :: OSI Approved :: MIT License
Classifier: Programming Language :: Python :: 3
Classifier: Programming Language :: Python :: 3.10
Classifier: Programming Language :: Python :: 3.11
Classifier: Programming Language :: Python :: 3.12
Classifier: Programming Language :: Python :: 3.13
Classifier: Programming Language :: Python :: 3.7
Classifier: Programming Language :: Python :: 3.9
Classifier: Topic :: Software Development :: Build Tools
Project-URL: Homepage, https://github.com/CALFEM/calfem-python
Requires-Python: >=3.9
Requires-Dist: gmsh
Requires-Dist: matplotlib
Requires-Dist: numpy
Requires-Dist: scipy
Requires-Dist: tabulate
Provides-Extra: visvis
Requires-Dist: visvis; extra == "visvis"
Provides-Extra: vedo
Requires-Dist: vedo; extra == "vedo"
Provides-Extra: pyvtk
Requires-Dist: pyvtk; extra == "pyvtk"
Provides-Extra: qtpy
Requires-Dist: qtpy; extra == "qtpy"
